aiolifx_scenes/__init__.py
aiolifx_scenes/main.py
aiolifx_scenes-0.1.0.dist-info/LICENSE
aiolifx_scenes-0.1.0.dist-info/METADATA
aiolifx_scenes-0.1.0.dist-info/WHEEL
aiolifx_scenes-0.1.0.dist-info/entry_points.txt
aiolifx_scenes-0.1.0.dist-info/RECORD
