Metadata-Version: 2.1
Name: aiolifx-scenes
Version: 0.1.0
Summary: AsyncIO library to extract scenes from the LIFX Cloud.
Home-page: https://github.com/Djelibeybi/aiolifx-scenes
License: MIT
Author: Avi Miller
Author-email: me@dje.li
Requires-Python: >=3.9,<4.0
Classifier: Development Status :: 2 - Pre-Alpha
Classifier: Intended Audience :: Developers
Classifier: License :: OSI Approved :: MIT License
Classifier: Natural Language :: English
Classifier: Programming Language :: Python :: 3
Classifier: Programming Language :: Python :: 3.9
Classifier: Programming Language :: Python :: 3.10
Classifier: Programming Language :: Python :: 3.11
Classifier: Programming Language :: Python :: 3.10
Classifier: Programming Language :: Python :: 3.11
Provides-Extra: dev
Requires-Dist: black (>=21.5b2,<22.0) ; extra == "dev"
Requires-Dist: bump2version (>=1.0.1,<2.0.0) ; extra == "dev"
Requires-Dist: httpx (>=0.23.3,<0.24.0)
Requires-Dist: httpx-auth (>=0.15.0,<0.16.0)
Requires-Dist: isort (>=5.8.0,<6.0.0) ; extra == "dev"
Requires-Dist: mypy (>=0.900,<0.901) ; extra == "dev"
